houses_client/__init__.py
houses_client/client.py
houses_client-1.3.0.dist-info/licenses/LICENSE
houses_client-1.3.0.dist-info/METADATA
houses_client-1.3.0.dist-info/WHEEL
houses_client-1.3.0.dist-info/top_level.txt
houses_client-1.3.0.dist-info/RECORD
