Metadata-Version: 2.4
Name: houses-client
Version: 1.3.0
Summary: Python SDK for HOUSES API
Author: Tim Tschampel
Author-email: Tim Tschampel <author@example.com>
Project-URL: Homepage, https://www.mayo.edu/research/centers-programs/mayo-clinic-houses-program/overview
Classifier: Programming Language :: Python :: 3
Classifier: License :: OSI Approved :: MIT License
Classifier: Operating System :: OS Independent
Requires-Python: >=3.9
License-File: LICENSE
Requires-Dist: oidc-client==0.2.6
Requires-Dist: requests==2.31.0
Dynamic: author
Dynamic: license-file
Dynamic: requires-python
